ros_test_interface_files-0.13.0.data/data/share/ament_index/resource_index/package_run_dependencies/test_interface_files
ros_test_interface_files-0.13.0.data/data/share/ament_index/resource_index/packages/test_interface_files
ros_test_interface_files-0.13.0.data/data/share/ament_index/resource_index/parent_prefix_path/test_interface_files
ros_test_interface_files-0.13.0.data/data/share/test_interface_files/local_setup.bash
ros_test_interface_files-0.13.0.data/data/share/test_interface_files/local_setup.dsv
ros_test_interface_files-0.13.0.data/data/share/test_interface_files/local_setup.sh
ros_test_interface_files-0.13.0.data/data/share/test_interface_files/local_setup.zsh
ros_test_interface_files-0.13.0.data/data/share/test_interface_files/package.dsv
ros_test_interface_files-0.13.0.data/data/share/test_interface_files/package.xml
ros_test_interface_files-0.13.0.data/data/share/test_interface_files/action/Fibonacci.action
ros_test_interface_files-0.13.0.data/data/share/test_interface_files/cmake/test_interface_files-extras.cmake
ros_test_interface_files-0.13.0.data/data/share/test_interface_files/cmake/test_interface_filesConfig-version.cmake
ros_test_interface_files-0.13.0.data/data/share/test_interface_files/cmake/test_interface_filesConfig.cmake
ros_test_interface_files-0.13.0.data/data/share/test_interface_files/environment/ament_prefix_path.dsv
ros_test_interface_files-0.13.0.data/data/share/test_interface_files/environment/ament_prefix_path.sh
ros_test_interface_files-0.13.0.data/data/share/test_interface_files/environment/path.dsv
ros_test_interface_files-0.13.0.data/data/share/test_interface_files/environment/path.sh
ros_test_interface_files-0.13.0.data/data/share/test_interface_files/msg/Arrays.msg
ros_test_interface_files-0.13.0.data/data/share/test_interface_files/msg/BasicTypes.msg
ros_test_interface_files-0.13.0.data/data/share/test_interface_files/msg/BoundedPlainSequences.msg
ros_test_interface_files-0.13.0.dist-info/METADATA
ros_test_interface_files-0.13.0.dist-info/WHEEL
ros_test_interface_files-0.13.0.dist-info/top_level.txt
ros_test_interface_files-0.13.0.dist-info/RECORD
ros_test_interface_files-0.13.0.dist-info/licenses/LICENSE
