Metadata-Version: 2.4
Name: ros-test-interface-files
Version: 0.13.0
Summary: Wheel for the test_interface_files (ros-test-interface-files) ROS 2 package.
License-File: LICENSE
Dynamic: description
Dynamic: description-content-type
Dynamic: license-file
Dynamic: summary
